<keymap version="1" name="Eclipse copy" parent="Eclipse">
  <action id="$Copy">
    <keyboard-shortcut first-keystroke="control C" />
    <keyboard-shortcut first-keystroke="meta C" />
  </action>
  <action id="$Cut">
    <keyboard-shortcut first-keystroke="control X" />
    <keyboard-shortcut first-keystroke="shift DELETE" />
    <keyboard-shortcut first-keystroke="meta X" />
  </action>
  <action id="$LRU">
    <keyboard-shortcut first-keystroke="shift meta alt O" />
  </action>
  <action id="$Paste">
    <keyboard-shortcut first-keystroke="control V" />
    <keyboard-shortcut first-keystroke="meta V" />
  </action>
  <action id="$Redo">
    <keyboard-shortcut first-keystroke="control Y" />
    <keyboard-shortcut first-keystroke="shift meta Z" />
  </action>
  <action id="$SelectAll">
    <keyboard-shortcut first-keystroke="control A" />
    <keyboard-shortcut first-keystroke="meta A" />
  </action>
  <action id="$Undo">
    <keyboard-shortcut first-keystroke="control Z" />
    <keyboard-shortcut first-keystroke="meta Z" />
  </action>
  <action id="ActivateChangesToolWindow">
    <keyboard-shortcut first-keystroke="alt 9" />
  </action>
  <action id="ActivateFloobitsChatToolWindow">
    <keyboard-shortcut first-keystroke="meta alt F" second-keystroke="meta alt C" />
  </action>
  <action id="Annotate">
    <keyboard-shortcut first-keystroke="shift meta alt A" />
  </action>
  <action id="Back">
    <keyboard-shortcut first-keystroke="meta alt LEFT" />
  </action>
  <action id="ChangeSignature">
    <keyboard-shortcut first-keystroke="shift meta C" />
  </action>
  <action id="CloseAllEditors">
    <keyboard-shortcut first-keystroke="shift control F4" />
    <keyboard-shortcut first-keystroke="shift control W" />
    <keyboard-shortcut first-keystroke="shift meta W" />
  </action>
  <action id="CloseAllEditorsButActive">
    <keyboard-shortcut first-keystroke="meta alt W" />
  </action>
  <action id="CloseContent">
    <keyboard-shortcut first-keystroke="control F4" />
    <keyboard-shortcut first-keystroke="meta F4" />
    <keyboard-shortcut first-keystroke="meta W" />
  </action>
  <action id="CloseProject">
    <keyboard-shortcut first-keystroke="shift meta alt W" />
  </action>
  <action id="Debug">
    <keyboard-shortcut first-keystroke="meta alt F10" />
  </action>
  <action id="DebugClass">
    <keyboard-shortcut first-keystroke="shift control alt F10" />
  </action>
  <action id="Diff.NextChange">
    <keyboard-shortcut first-keystroke="control F6" />
    <keyboard-shortcut first-keystroke="alt TAB" />
    <keyboard-shortcut first-keystroke="control alt RIGHT" />
  </action>
  <action id="Diff.PrevChange">
    <keyboard-shortcut first-keystroke="shift control F6" />
    <keyboard-shortcut first-keystroke="shift alt TAB" />
    <keyboard-shortcut first-keystroke="control alt LEFT" />
  </action>
  <action id="Editor Copy">
    <keyboard-shortcut first-keystroke="meta C" />
  </action>
  <action id="Editor Cut">
    <keyboard-shortcut first-keystroke="meta X" />
  </action>
  <action id="Editor LRU">
    <keyboard-shortcut first-keystroke="shift meta alt O" />
  </action>
  <action id="Editor Paste">
    <keyboard-shortcut first-keystroke="meta V" />
  </action>
  <action id="Editor Redo">
    <keyboard-shortcut first-keystroke="shift meta Z" />
  </action>
  <action id="Editor SelectAll">
    <keyboard-shortcut first-keystroke="meta A" />
  </action>
  <action id="Editor Undo">
    <keyboard-shortcut first-keystroke="meta Z" />
  </action>
  <action id="EditorDeleteLine">
    <keyboard-shortcut first-keystroke="control D" />
    <keyboard-shortcut first-keystroke="meta D" />
  </action>
  <action id="EditorDuplicate">
    <keyboard-shortcut first-keystroke="shift control D" />
    <keyboard-shortcut first-keystroke="shift meta D" />
  </action>
  <action id="EditorLineEnd">
    <keyboard-shortcut first-keystroke="END" />
    <keyboard-shortcut first-keystroke="control RIGHT" />
    <keyboard-shortcut first-keystroke="meta RIGHT" />
  </action>
  <action id="EditorLineEndWithSelection">
    <keyboard-shortcut first-keystroke="shift END" />
    <keyboard-shortcut first-keystroke="shift meta RIGHT" />
  </action>
  <action id="EditorLineStart">
    <keyboard-shortcut first-keystroke="HOME" />
    <keyboard-shortcut first-keystroke="control LEFT" />
    <keyboard-shortcut first-keystroke="meta LEFT" />
  </action>
  <action id="EditorLineStartWithSelection">
    <keyboard-shortcut first-keystroke="shift HOME" />
    <keyboard-shortcut first-keystroke="shift meta LEFT" />
  </action>
  <action id="EditorNextWord">
    <keyboard-shortcut first-keystroke="alt RIGHT" />
  </action>
  <action id="EditorPreviousWord">
    <keyboard-shortcut first-keystroke="alt LEFT" />
  </action>
  <action id="EditorTextEnd">
    <keyboard-shortcut first-keystroke="control END" />
    <keyboard-shortcut first-keystroke="meta DOWN" />
  </action>
  <action id="EditorTextEndWithSelection">
    <keyboard-shortcut first-keystroke="shift control END" />
    <keyboard-shortcut first-keystroke="shift meta DOWN" />
  </action>
  <action id="EditorTextStart">
    <keyboard-shortcut first-keystroke="control HOME" />
    <keyboard-shortcut first-keystroke="meta UP" />
  </action>
  <action id="EditorTextStartWithSelection">
    <keyboard-shortcut first-keystroke="shift control HOME" />
    <keyboard-shortcut first-keystroke="shift meta UP" />
  </action>
  <action id="EditorToggleColumnMode">
    <keyboard-shortcut first-keystroke="meta alt C" />
  </action>
  <action id="EditorToggleUseSoftWraps">
    <keyboard-shortcut first-keystroke="control meta alt W" />
  </action>
  <action id="ExtractMethod">
    <keyboard-shortcut first-keystroke="shift meta M" />
  </action>
  <action id="FileStructurePopup">
    <keyboard-shortcut first-keystroke="meta O" />
  </action>
  <action id="Find">
    <keyboard-shortcut first-keystroke="control H" />
  </action>
  <action id="FindInPath">
    <keyboard-shortcut first-keystroke="shift meta alt G" />
  </action>
  <action id="FindUsages">
    <keyboard-shortcut first-keystroke="shift meta G" />
  </action>
  <action id="FindUsagesInFile">
    <keyboard-shortcut first-keystroke="meta U" />
  </action>
  <action id="Forward">
    <keyboard-shortcut first-keystroke="meta alt RIGHT" />
  </action>
  <action id="GotoAction">
    <keyboard-shortcut first-keystroke="meta alt A" />
  </action>
  <action id="GotoFile">
    <keyboard-shortcut first-keystroke="shift control R" />
    <keyboard-shortcut first-keystroke="shift control N" />
  </action>
  <action id="GotoSuperMethod">
    <keyboard-shortcut first-keystroke="meta alt T" />
  </action>
  <action id="HighlightUsagesInFile">
    <keyboard-shortcut first-keystroke="shift meta U" />
  </action>
  <action id="Inline">
    <keyboard-shortcut first-keystroke="shift meta I" />
  </action>
  <action id="IntroduceField">
    <keyboard-shortcut first-keystroke="shift meta F" />
  </action>
  <action id="IntroduceParameter">
    <keyboard-shortcut first-keystroke="shift meta P" />
  </action>
  <action id="IntroduceVariable">
    <keyboard-shortcut first-keystroke="shift meta L" />
  </action>
  <action id="MinimizeCurrentWindow">
    <keyboard-shortcut first-keystroke="meta M" />
  </action>
  <action id="Move">
    <keyboard-shortcut first-keystroke="shift meta V" />
  </action>
  <action id="NextDiff">
    <keyboard-shortcut first-keystroke="alt DOWN" />
  </action>
  <action id="NextTab">
    <keyboard-shortcut first-keystroke="control F6" />
    <keyboard-shortcut first-keystroke="alt TAB" />
    <keyboard-shortcut first-keystroke="control alt RIGHT" />
  </action>
  <action id="PreviousDiff">
    <keyboard-shortcut first-keystroke="alt UP" />
  </action>
  <action id="PreviousTab">
    <keyboard-shortcut first-keystroke="shift control F6" />
    <keyboard-shortcut first-keystroke="shift alt TAB" />
    <keyboard-shortcut first-keystroke="control alt LEFT" />
  </action>
  <action id="ReformatCode">
    <keyboard-shortcut first-keystroke="control alt L" />
    <keyboard-shortcut first-keystroke="shift control F" />
    <keyboard-shortcut first-keystroke="meta F" />
  </action>
  <action id="RenameElement">
    <keyboard-shortcut first-keystroke="shift meta R" />
  </action>
  <action id="RestoreDefaultLayout">
    <keyboard-shortcut first-keystroke="meta F12" />
  </action>
  <action id="Run">
    <keyboard-shortcut first-keystroke="meta F10" />
  </action>
  <action id="SaveAll">
    <keyboard-shortcut first-keystroke="control S" />
    <keyboard-shortcut first-keystroke="meta S" />
  </action>
  <action id="ShowRegistry">
    <keyboard-shortcut first-keystroke="shift control meta alt OPEN_BRACKET" />
  </action>
  <action id="ShowUsages">
    <keyboard-shortcut first-keystroke="control alt F7" />
    <keyboard-shortcut first-keystroke="meta G" />
  </action>
  <action id="SplitVertically">
    <keyboard-shortcut first-keystroke="meta alt S" />
  </action>
  <action id="StepInto">
    <keyboard-shortcut first-keystroke="F5" />
  </action>
  <action id="SwitchApply">
    <keyboard-shortcut first-keystroke="control alt ENTER" />
  </action>
  <action id="SwitchDown">
    <keyboard-shortcut first-keystroke="control alt DOWN" />
  </action>
  <action id="SwitchLeft">
    <keyboard-shortcut first-keystroke="control alt LEFT" />
  </action>
  <action id="SwitchRight">
    <keyboard-shortcut first-keystroke="control alt RIGHT" />
  </action>
  <action id="SwitchUp">
    <keyboard-shortcut first-keystroke="control alt UP" />
  </action>
  <action id="Synchronize" />
  <action id="Uml.ShowDiff" />
  <action id="Unscramble">
    <keyboard-shortcut first-keystroke="meta E" />
  </action>
  <action id="UnsplitAll">
    <keyboard-shortcut first-keystroke="control meta alt S" />
  </action>
  <action id="Vcs.ShowTabbedFileHistory">
    <keyboard-shortcut first-keystroke="shift meta alt H" />
  </action>
  <action id="floobits.actions.FollowMode">
    <keyboard-shortcut first-keystroke="meta alt F" second-keystroke="meta alt F" />
  </action>
  <action id="floobits.actions.LeaveWorkspace">
    <keyboard-shortcut first-keystroke="meta alt F" second-keystroke="meta alt W" />
  </action>
  <action id="floobits.actions.OpenProjectInWorkspace">
    <keyboard-shortcut first-keystroke="meta alt F" second-keystroke="meta alt J" />
  </action>
  <action id="floobits.actions.OpenWorkspaceInBrowser">
    <keyboard-shortcut first-keystroke="meta alt F" second-keystroke="meta alt V" />
  </action>
  <action id="floobits.actions.Summon">
    <keyboard-shortcut first-keystroke="meta alt F" second-keystroke="meta alt S" />
  </action>
  <action id="toggle_camel_snake_case">
    <keyboard-shortcut first-keystroke="meta alt U" />
  </action>
</keymap>